mcp_zepai/__init__.py
mcp_zepai/__main__.py
mcp_zepai/constants.py
mcp_zepai/server.py
mcp_zepai/tool_schema.py
mcp_zepai/tools.py
syia_mcp_zaepai_2025_x7k9-0.1.20.dist-info/METADATA
syia_mcp_zaepai_2025_x7k9-0.1.20.dist-info/WHEEL
syia_mcp_zaepai_2025_x7k9-0.1.20.dist-info/top_level.txt
syia_mcp_zaepai_2025_x7k9-0.1.20.dist-info/RECORD
