Metadata-Version: 2.4
Name: syia-mcp-zaepai-2025-x7k9
Version: 0.1.20
Summary: MCP ZepAi Module
Project-URL: Repository, https://github.com/syia-ai/mcp-data-science
Project-URL: Homepage, https://github.com/syia-ai/mcp-data-science
Requires-Python: >=3.12
Requires-Dist: asyncio>=3.4.3
Requires-Dist: mcp>=1.10.1
Requires-Dist: zep-cloud>=2.17.0
